{
  "main": [
    {
      "name": "首頁",
      "url": "/"
    },
    {
      "name": "關於zE",
      "url": "/about"
    },
    {
      "name": "和我聯絡",
      "url": "/contact"
    },
    {
      "name": "頁面",
      "url": "",
      "hasChildren": true,
      "children": [
        {
          "name": "作者",
          "url": "/authors"
        },
        {
          "name": "分類",
          "url": "/categories"
        },
        {
          "name": "標籤",
          "url": "/tags"
        },
        {
          "name": "元素",
          "url": "/elements"
        },
        {
          "name": "聲明",
          "url": "/privacy-policy"
        }
      ]
    }
  ],
  "footer": [
    {
      "name": "About",
      "url": "/about"
    },
    {
      "name": "Contact",
      "url": "/contact"
    },
    {
      "name": "Elements",
      "url": "/elements"
    },
    {
      "name": "Privacy Policy",
      "url": "/privacy-policy"
    }
  ]
}
